Metadata-Version: 1.0
Name: trumpet-scraper
Version: 0.0.1
Summary: Package that scrapes trumpet specifications
Home-page: UNKNOWN
Author: Christopher Hammond
Author-email: UNKNOWN
License: UNKNOWN
Platform: UNKNOWN
